mdacli/__init__.py
mdacli/__main__.py
mdacli/_version.py
mdacli/cli.py
mdacli/colors.py
mdacli/libcli.py
mdacli/logger.py
mdacli/save.py
mdacli/utils.py
mdacli-0.1.33.dist-info/licenses/LICENSE
mdacli-0.1.33.dist-info/METADATA
mdacli-0.1.33.dist-info/WHEEL
mdacli-0.1.33.dist-info/entry_points.txt
mdacli-0.1.33.dist-info/top_level.txt
mdacli-0.1.33.dist-info/RECORD
