Metadata-Version: 2.4
Name: mdacli
Version: 0.1.33
Summary: A command line client for MDAnalysis Analysis classes.
Author-email: MDAnalysis Development Team and contributors <mdanalysis@numfocus.org>
License: GPL-3.0-or-later
Project-URL: homepage, https://mdacli.mdanalysis.org
Project-URL: documentation, https://mdacli.mdanalysis.org
Project-URL: repository, https://github.com/MDAnalysis/mdacli
Project-URL: changelog, https://github.com/MDAnalysis/mdacli/blob/main/docs/CHANGELOG.rst
Project-URL: issues, https://github.com/MDAnalysis/mdacli/issues/
Project-URL: discord, https://discord.com/channels/807348386012987462
Project-URL: twitter, https://twitter.com/mdanalysis
Project-URL: blog, https://www.mdanalysis.org/blog
Project-URL: user_group,  https://groups.google.com/g/mdnalysis-discussion
Keywords: python,cli,science,command-line,molecular-dynamics,computational-chemistry,molecular-dynamics-simulation,command-line-tool,trajectory-analysis mdanalysis
Classifier: Development Status :: 4 - Beta
Classifier: Environment :: Console
Classifier: License :: OSI Approved :: GNU General Public License v3 (GPLv3)
Classifier: Intended Audience :: Science/Research
Classifier: Natural Language :: English
Classifier: Operating System :: POSIX
Classifier: Operating System :: MacOS :: MacOS X
Classifier: Operating System :: Microsoft :: Windows
Classifier: Programming Language :: Python :: 3
Classifier: Topic :: Scientific/Engineering
Classifier: Topic :: Scientific/Engineering :: Bio-Informatics
Classifier: Topic :: Scientific/Engineering :: Chemistry
Classifier: Topic :: Scientific/Engineering :: Physics
Classifier: Topic :: Software Development :: Libraries :: Python Modules
Classifier: Topic :: System :: Shells
Requires-Python: >=3.11
License-File: LICENSE
Requires-Dist: MDAnalysis>=2.10.0
Requires-Dist: threadpoolctl
Dynamic: license-file
